{"metadata": {"organization_names": [], "person_names_verified": [], "topics": [], "vars": {}, "terms": ["**(AS AMENDED DECEMBER 16, 2009)**", "**(AS AMENDED [[Date 4: Date]])**", "**,**", "**Cumulative Number of Shares**", "**Date of Board/Committee Approval**", "**EXHIBIT A**", "**Number of Shares Added**", "**Page**", "**SCHEDULE OF SHARES RESERVED FOR ISSUANCE UNDER THE PLAN**", "**TABLE OF CONTENTS**", "**THERAVANCE, INC. 2008 NEW EMPLOYEE EQUITY INCENTIVE PLAN (AS ADOPTED EFFECTIVE [[Date 1: Date]])**", "**THERAVANCE, INC. 2008 NEW EMPLOYEE EQUITY INCENTIVE PLAN**", "**not**", "\u201c**Affiliate**\u201d", "\u201c**Award**\u201d", "\u201c**Board**\u201d", "\u201c**Change in Control**\u201d", "\u201c**Code**\u201d", "\u201c**Committee**\u201d", "\u201c**Common Share**\u201d", "\u201c**Consultant**\u201d", "\u201c**Corporation**\u201d", "\u201c**Employee**\u201d", "\u201c**Exchange Act**\u201d", "\u201c**Exercise Price**", "\u201c**Fair Market Value**\u201d", "\u201c**NSO**\u201d", "\u201c**Option**\u201d", "\u201c**Optionee**\u201d", "\u201c**Parent**\u201d", "\u201c**Participant**\u201d", "\u201c**Plan**\u201d", "\u201c**Restricted Share**\u201d", "\u201c**Restricted Stock Agreement**\u201d", "\u201c**Service**\u201d", "\u201c**Stock Option Agreement**\u201d", "\u201c**Stock Unit Agreement**\u201d", "\u201c**Stock Unit**\u201d", "\u201c**Subsidiary**\u201d", "\u201cGSK\u201d", "\u201cGovernance Agreement\u201d", "\u201cOriginal Directors\u201d"], "person_names": [], "organization_names_verified": ["glaxo group", "smithkline beecham corporation", "theravance, inc."], "agreement_id": "9b0f2669f730f52d122eb7970f06e66d2b8197fcb733e1d8473bf9dab133c314"}}