{"metadata": {"organization_names": [], "person_names_verified": ["steven davidson", "kathy bolmer", "brent turner", "jack polson", "christopher howard", "ronald fincher", "joey jacobs", "keith e. thompson", "james h. nixon iii", "eliza w. swann", "peter d. lyons", "chris howard", "minh van ngo", "james c. woolery", "debra osteen"], "organization_names_verified": ["universal health services inc", "universal health services inc.", "{psychiatric solutions inc", "psychiatric solutions inc", "cravath, swaine & moore", "psi surety, inc.", "jpmorgan chase bank, n.a.", "goldman sachs & co.", "the psychiatric solutions, inc.", "the psychiatric solutions", "psychiatric solutions", "olympus acquisition corp.", "universal health services", "the surviving corporation"], "topics": [], "entities_rejected": [], "person_names": ["waller lansden dortch"], "agreement_id": "8ec3b7100576128ed6d6002e31e0fd3a4a25155c96f597dcf82a57ac35882bf0", "vars": {}, "terms": ["**ADDITIONAL AGREEMENTS**", "**CONDITIONS TO THE MERGER**", "**CONDUCT OF BUSINESS PENDING THE MERGER**", "**CONFIDENTIAL**", "**CONVERSION OF SECURITIES; EXCHANGE OF CERTIFICATES**", "**GENERAL PROVISIONS**", "**Page**", "**RECITALS**", "**REPRESENTATIONS AND WARRANTIES OF PARENT AND MERGER SUB**", "**REPRESENTATIONS AND WARRANTIES OF THE COMPANY**", "**TERMINATION, AMENDMENT AND WAIVER**", "**THE MERGER**", "**Table of Contents**", "*further*", "*however*", "*minus*", "*provided*", "*provided, further*", "*provided, however*", "\u201c Action\u201d", "\u201c Certificate of Merger\u201d", "\u201c Closing\u201d", "\u201c Company Permits\u201d", "\u201c Company Preferred Stock\u201d", "\u201c Dissenting Shares\u201d", "\u201c ERISA\u201d", "\u201c Environmental Laws\u201d", "\u201c Exchange Fund\u201d", "\u201c Financing\u201d", "\u201c Material Contracts\u201d", "\u201c Owned Real Property\u201d", "\u201c Paying Agent\u201d", "\u201c Real Property Leases\u201d", "\u201c Section 262\u201d", "\u201c Surviving Corporation\u201d", "\u201cAgreement\u201d", "\u201cBook-Entry Shares\u201d", "\u201cCertificates\u201d", "\u201cCompany Board\u201d", "\u201cCompany Common Stock\u201d", "\u201cCompany Disclosure Schedule\u201d", "\u201cCompany Stockholders\u2019 Meeting\u201d", "\u201cCompany Termination Fee\u201d", "\u201cCompany\u201d", "\u201cConfidentiality Agreement\u201d", "\u201cDGCL\u201d", "\u201cEnd Date\u201d", "\u201cExchange Act\u201d", "\u201cExpense Reimbursement\u201d", "\u201cGAAP\u201d", "\u201cGovernmental Authority\u201d", "\u201cHSR Act\u201d", "\u201cIRS\u201d", "\u201cMerger Consideration\u201d", "\u201cMerger Sub\u201d", "\u201cMerger\u201d", "\u201cNotice of Adverse Action\u201d", "\u201cParent\u201d", "\u201cRegulatory Condition\u201d", "\u201cSEC\u201d", "\u201cSecurities Act\u201d", "\u201cShares\u201d", "\u201cStockholder Approval\u201d", "\u201cVoting Company Debt\u201d", "\u201ccontrolled by\u201d and \u201cunder common control with\u201d"]}}