{"metadata": {"organization_names": [], "person_names_verified": [], "organization_names_verified": ["jabil circuit, inc."], "topics": [], "entities_rejected": [], "person_names": [], "agreement_id": "9640649b847d32d1de818d47550ca17f2e01bb102183bcbae0b959e518d83f73", "vars": {}, "terms": ["**JABIL CIRCUIT, INC. 2002 STOCK INCENTIVE PLAN**", "\u201c$[[USD Value 1]] Limit\u201d", "\u201c60-Day Period\u201d", "\u201cAcquired Entity Option\u201d", "\u201cAcquired Entity\u201d", "\u201cAcquisition\u201d", "\u201cChange in Control Anniversary\u201d", "\u201cCompensation Committee\u201d", "\u201cCurrent Grant\u201d", "\u201cNASDAQ\u201d", "\u201cOther Plans\u201d", "\u201cPrior Grants\u201d"]}}