{"metadata": {"organization_names": [], "person_names_verified": ["debin chen", "wang yu mai zi", "zhou xigen", "ding jie", "chen debin", "jie ding"], "organization_names_verified": ["china merchants bank"], "topics": [], "entities_rejected": [], "person_names": [], "agreement_id": "b95fd6c1fb8b648508220644200c894acb6c3781f63e35f41c0cb1be9d669055", "vars": {}, "terms": ["**4682 0375 5656 5819**", "**House Rental Agreement**", "**Supplementary Agreement**", "*/s/ Ding Jie___*", "*_/s/ Chen Debin_______*", "\u201cthe apartment\u201d", "\u201cthe main agreement\u201d or \u201cthe Agreement\u201d", "\u201cthe property\u201d"]}}