{"metadata": {"organization_names": [], "person_names_verified": [], "organization_names_verified": ["motricity inc", "motricity, inc", "eastward capital partners iv", "motricity, inc."], "vars": {}, "entities_rejected": [], "person_names": [], "agreement_id": "cdf1fe9ccd368a1c126b47cc02ef99ecabe25421f25b36866d9d06072dfc0780", "topics": [], "terms": ["**FORM OF SUBSCRIPTION**", "**MOTRICITY, INC.**", "**THIS WARRANT AND THE SHARES OF COMMON STOCK ISSUABLE UPON THE EXERCISE HEREOF HAVE NOT BEEN REGISTERED UNDER THE SECURITIES ACT OF 1933, AS AMENDED, OR UNDER ANY STATE SECURITIES LAWS AND MAY NOT BE SOLD, ASSIGNED, PLEDGED, HYPOTHECATED OR TRANSFERRED UNLESS THERE EXISTS AN EFFECTIVE REGISTRATION STATEMENT THEREFOR UNDER THE SECURITIES ACT OF 1933, AS AMENDED, AND ALL APPLICABLE STATE SECURITIES LAWS OR THE ISSUER HEREOF HAS RECEIVED AN OPINION OF COUNSEL, REASONABLY SATISFACTORY TO COUNSEL OF THE ISSUER, THAT SUCH SALE, ASSIGNMENT, PLEDGE, HYPOTHECATION OR TRANSFER IS EXEMPT FROM REGISTRATION.**", "*The Wall Street Journal*", "\u201cAct\u201d", "\u201cCertificate\u201d", "\u201cCommon Stock\u201d", "\u201cCompany\u201d", "\u201cConversion Price of the Series F Preferred Stock, Series E Preferred Stock and Series D1 Preferred Stock\u201d in such provisions being replaced with the term \u201cPurchase Price\u201d", "\u201cExpiration Date\u201d", "\u201cPublic Offering\u201d", "\u201cRights Agreement\u201d"]}}