{"metadata": {"organization_names": [], "person_names_verified": [], "organization_names_verified": ["international technidyne corporation"], "topics": [], "entities_rejected": [], "person_names": [], "agreement_id": "ceb2e528f90f427d880d03f66f6362ac4294ef8b33c91c5c4577e25bf0743d45", "vars": {}, "terms": ["*         %    $   *", "* ([[Percentage 5: Number]]% of target) no payment is earned for that objective. If ITC NGIBT earnings is less than $*", "***", "**Authority.**", "**Award**", "**Bonus Opportunity and Award**", "**Determination Of The Fund**", "**Effective Date**", "**Eligibility**", "**Financial Objectives (*****", "**General Provisions**", "**Goal**", "**ITC**", "**Incentive Objectives**", "**Non-GAAP Income Before Tax**", "**Objective**", "**Over-Achievement Award Opportunity/Performance Accelerator**", "**Performance Goal and Payout**", "**Personal Objectives (*****", "**Plan Administration**", "**Plan: FY10 Executive Incentive Plan Division: International Technidyne Corporation (ITC)**", "**Prorated Awards.**", "**Revenue**", "**Transfers.**", "\u201cCEO\u201d"]}}