{"metadata": {"organization_names": [], "person_names_verified": ["laura e. anthony"], "organization_names_verified": ["genesis capital acquisition corp.", "genesis capital corporation", "football club, inc.", "football, inc.", "address football club inc."], "vars": {"Party": {"Gary Miller": "[[Party 4]]", "Michael Whitely": "[[Party 6]]", "Bradley David LaCombe": "[[Party 3]]", "Richard Astrom": "[[Party 2]]", "Todd D. Hansen": "[[Party 7]]", "Michael Carpenter": "[[Party 5]]", "Andrew Vallozzi III": "[[Party 1]]"}}, "entities_rejected": [], "person_names": [], "agreement_id": "50b4a461241fa0404bebe03239a1098cef6a2123394aea2527ef56cab57fbe28", "topics": [], "terms": ["**.**", "**3(d)**", "**CONDITIONS TO CONSUMMATION OF THE UNWIND**", "**Exhibit 3(a)**", "**Exhibit 3(b)**", "**Exhibit 3(c)**", "**Exhibit 3(e).**", "**Exhibit**", "**MISCELLANEOUS**", "**RECITALS.**", "**REPRESENTATIONS AND WARRANTIES OF IRON**", "**REPRESENTATIONS AND WARRANTIES OF THE MEMBERS**", "**TERMINATION**", "**THE CLOSING**", "**TRANSACTIONS RELATED TO THE UNWIND**", "**UNWIND AGREEMENT**", "**UNWIND**", "**bers**\u201d", "\u2019) properties, except as otherwise provided for herein or by applicable law. From and after the Closing Date, Iron and its Affiliates shall cease to have any rights with respect to Iron Sub, the Iron Sub Shares and any of the Iron Subs (and its Affiliates\u2019", "\u201c**Agreement**\u201d", "\u201c**Closing Date**", "\u201c**Closing**\u201d", "\u201c**Iron Shares**\u201d", "\u201c**Iron Sub Shares**\u201d", "\u201c**Iron Sub**\u201d", "\u201c**Iron**\u201d", "\u201c**MIPAF**\u201d", "\u201c**Me**", "\u201c**Me**m**bers**\u201d", "\u201c**Merger Agreement**\u201d", "\u201c**Merger**\u201d", "\u201c**Outside Date**\u201d", "\u201c**WPAFI**\u201d", "\u201cGuarantors\u201d", "\u201cMembers\u201d"]}}