{"metadata": {"organization_names": [], "person_names_verified": [], "organization_names_verified": ["bank of texas n.a.", "willbros united states holdings inc", "infrastrux group", "the bank of new york mellon", "infrastrux group, inc.", "bank of texas", "willbros united states holdings", "willbros usa, inc.", "the bank of new york"], "topics": [], "entities_rejected": [], "person_names": [], "agreement_id": "fbcbe277f5009e05a7b1ac2184ab9c2bffbbb2ed3d54f7b8ef8a11c5a2022681", "vars": {"Party": {"Willbros Group, Inc.": "[[Party 1]]"}}, "terms": ["**AMENDMENT TO CONSENT AGREEMENT**", "**\u201cPermitted Indebtedness\u201d**", "*[signatures on following page]*", "\u201cAcquisition Date\u201d", "\u201cAmendment\u201d", "\u201cCompany\u201d", "\u201cConsenting Holder\u201d", "\u201cEffective Date\u201d", "\u201cFirst Supplemental Indenture\u201d", "\u201cGuarantor\u201d", "\u201cMerger Agreement\u201d", "\u201cMerger\u201d", "\u201cModified Third Supplemental Indenture\u201d", "\u201cNotes\u201d", "\u201cOriginal Third Supplemental Indenture\u201d", "\u201cSecond Supplemental Indenture,\u201d and such indenture as so supplemented by the First Supplemental Indenture and the Second Supplemental Indenture, the \u201cIndenture\u201d", "\u201cSpecial Interest Payment Record Date\u201d", "\u201cSpecial Interest Payment\u201d", "\u201cSpecial Interest\u201d", "\u201cSub\u201d", "\u201cTrustee\u201d", "\u201cWillbros Panama\u201d"]}}