{"metadata": {"organization_names": [], "person_names_verified": [], "organization_names_verified": ["atlas pipeline partners gp", "atlas pipeline partners l.p.", "atlas pipeline partners"], "topics": [], "entities_rejected": [], "person_names": [], "agreement_id": "e23a97dcb508a6dc1cc42f315a7d6db4f4744b5e0ae6cffc78e89d18936b92ab", "vars": {}, "terms": ["**AMENDMENT NO. 8**", "**ATLAS PIPELINE PARTNERS, L.P.**", "**OF**", "**PARTNERSHIP**", "**SECOND AMENDED AND RESTATED AGREEMENT OF LIMITED**", "**TO**", "\u201cAmendment\u201d", "\u201cClass C Preferred Certificate of Designation\u201d", "\u201cGeneral Partner\u201d", "\u201cLimited Partnership Agreement\u201d", "\u201cPartnership\u201d"]}}