{"metadata": {"organization_names": [], "person_names_verified": ["jonathan f. irwin"], "organization_names_verified": [], "topics": [], "entities_rejected": [], "person_names": [], "agreement_id": "5d8b860061b525f3e55f206a194a3713c0e3c187983588cf8e244ed7566dfa9d", "vars": {"Party": {"Judd Handler": "[[Party 2]]", "Frozen Food Gift Group, Inc.": "[[Party 1]]"}}, "terms": ["\"AAA\"", "**Arbitration**", "**Character and Extent of Services**", "**Compensation**", "**Confidentiality**", "**Counterparts and Facsimile**", "**Covenant Not to Compete**", "**Expenses.**", "**Governing Law**", "**INDEPENDENT CONTRACTOR AGREEMENT**", "**INDEPENDENT CONTRACTOR**", "**Indemnification**", "**Independent Contractor**", "**Ownership of Developments**", "**Remedies**", "**Representations of CONTRACTOR**", "**Term**", "**Termination**", "**per**", "**se**", "\u201cAgreement\u201d", "\u201cCompany\u201d", "\u201cContractor\u201d"]}}