{"metadata": {"organization_names": [], "person_names_verified": [], "organization_names_verified": ["herbalife ltd", "herbalife ltd."], "vars": {}, "entities_rejected": [], "person_names": [], "agreement_id": "f6659b7fba919698641f2cf0029c65e6e2e611612f737336b6558c42bd228d50", "topics": [], "terms": ["**HERBALIFE LTD. 2005 STOCK INCENTIVE PLAN**", "**INDEPENDENT DIRECTORS STOCK APPRECIATION RIGHT AGREEMENT**", "\u201cAgreement\u201d", "\u201cAward\u201d", "\u201cCommon Shares\u201d", "\u201cCompany\u201d", "\u201cGrant Date\u201d", "\u201cIndependent Directors Plan\u201d", "\u201cParticipant\u201d", "\u201cVesting Date\u201d"]}}