{"metadata": {"organization_names": [], "person_names_verified": ["glenn r james", "judi, harold", "glenn r. james", "terrance d. paul"], "organization_names_verified": ["learning, inc.", "renaissance learning, inc."], "vars": {}, "entities_rejected": [], "person_names": [], "agreement_id": "e1d774acb6a84b0070198646040660d1ae6f851b4176ef1cc75f542676e4b6de", "topics": [], "terms": ["**GLENN R. JAMES**", "**Offer of Employment**", "*/s/ Glenn R. James, [[Date 6: Date]]*", "*Glenn R. James (Signature and date)*", "*with Renaissance Learning on [[Date 5: Date]].*", "\u201cPlan\u201d"]}}