{"metadata": {"organization_names": [], "person_names_verified": ["sidney w. swartz"], "organization_names_verified": ["the timberland company"], "vars": {}, "entities_rejected": [], "person_names": [], "agreement_id": "ca4b528c41d19d89372fb824ac99ed3513a4cc43fab229bfec14528a5c5fd401", "topics": [], "terms": ["*(effective 1/1/10)*", "**THE TIMBERLAND COMPANY 2010 EXECUTIVE LONG TERM INCENTIVE PROGRAM**", "**THE TIMBERLAND COMPANY**", "*Administration*", "*Agreements*", "*Award Payment*", "*Award Payout Calculation and Approval*", "*Awards*", "*Definitions*", "*Employment*", "*Participation*", "*Performance Measures and Performance Goals*", "*Purpose*", "*Vesting of PSOs*", "*and further provided*", "*provided*"]}}